odoo/addons/website_sale_loyalty_suggestion_wizard_multi_gift/README.rst
odoo/addons/website_sale_loyalty_suggestion_wizard_multi_gift/__init__.py
odoo/addons/website_sale_loyalty_suggestion_wizard_multi_gift/__manifest__.py
odoo/addons/website_sale_loyalty_suggestion_wizard_multi_gift/controllers/__init__.py
odoo/addons/website_sale_loyalty_suggestion_wizard_multi_gift/controllers/promotion_wizard.py
odoo/addons/website_sale_loyalty_suggestion_wizard_multi_gift/i18n/it.po
odoo/addons/website_sale_loyalty_suggestion_wizard_multi_gift/i18n/website_sale_loyalty_suggestion_wizard_multi_gift.pot
odoo/addons/website_sale_loyalty_suggestion_wizard_multi_gift/readme/CONTRIBUTORS.md
odoo/addons/website_sale_loyalty_suggestion_wizard_multi_gift/readme/DESCRIPTION.md
odoo/addons/website_sale_loyalty_suggestion_wizard_multi_gift/readme/USAGE.md
odoo/addons/website_sale_loyalty_suggestion_wizard_multi_gift/static/description/icon.png
odoo/addons/website_sale_loyalty_suggestion_wizard_multi_gift/static/description/index.html
odoo/addons/website_sale_loyalty_suggestion_wizard_multi_gift/templates/wizard_templates.xml
odoo_addon_website_sale_loyalty_suggestion_wizard_multi_gift-18.0.1.0.0.2.dist-info/METADATA
odoo_addon_website_sale_loyalty_suggestion_wizard_multi_gift-18.0.1.0.0.2.dist-info/WHEEL
odoo_addon_website_sale_loyalty_suggestion_wizard_multi_gift-18.0.1.0.0.2.dist-info/top_level.txt
odoo_addon_website_sale_loyalty_suggestion_wizard_multi_gift-18.0.1.0.0.2.dist-info/RECORD
